CONTRIBUTING.rst
HISTORY.rst
LICENSE
MANIFEST.in
README.rst
setup.cfg
setup.py
angelspie/__init__.py
angelspie/autogenerated.py
angelspie/cli.py
angelspie/config.py
angelspie/logic.py
angelspie/script.py
angelspie/xtest.py
angelspie.egg-info/PKG-INFO
angelspie.egg-info/SOURCES.txt
angelspie.egg-info/dependency_links.txt
angelspie.egg-info/entry_points.txt
angelspie.egg-info/not-zip-safe
angelspie.egg-info/top_level.txt
docs/Makefile
docs/conf.py
docs/contributing.rst
docs/history.rst
docs/index.rst
docs/installation.rst
docs/make.bat
docs/readme.rst
docs/usage.rst