Metadata-Version: 2.1
Name: angelspie
Version: 0.1.6
Summary: mapping global hotkeys and various actions for X11 events
Home-page: https://github.com/pawnhearts/angelspie
Author: robotnaoborot
Author-email: robotnaoborot@gmail.com
License: MIT license
Keywords: angelspie
Platform: UNKNOWN
Classifier: Development Status :: 2 - Pre-Alpha
Classifier: Intended Audience :: Developers
Classifier: License :: OSI Approved :: MIT License
Classifier: Natural Language :: English
Classifier: Programming Language :: Python :: 3
Classifier: Programming Language :: Python :: 3.6
Classifier: Programming Language :: Python :: 3.7
Classifier: Programming Language :: Python :: 3.8
Requires-Python: >=3.6
